{
  "SaveName": "",
  "Date": "",
  "VersionNumber": "",
  "GameMode": "",
  "GameType": "",
  "GameComplexity": "",
  "Tags": [],
  "Gravity": 0.5,
  "PlayArea": 0.5,
  "Table": "",
  "Sky": "",
  "Note": "",
  "TabStates": {},
  "LuaScript": "",
  "LuaScriptState": "",
  "XmlUI": "",
  "ObjectStates": [
    {
      "GUID": "f8da18",
      "Name": "Bag",
      "Transform": {
        "posX": 15.2750254,
        "posY": 0.784764767,
        "posZ": -11.0700006,
        "rotX": 3.004917E-06,
        "rotY": -2.427875E-06,
        "rotZ": 0.00164421089,
        "scaleX": 1.0,
        "scaleY": 1.0,
        "scaleZ": 1.0
      },
      "Nickname": "Sound Buttons",
      "Description": "",
      "GMNotes": "",
      "AltLookAngle": {
        "x": 0.0,
        "y": 0.0,
        "z": 0.0
      },
      "ColorDiffuse": {
        "r": 0.7058823,
        "g": 0.366520882,
        "b": 0.0
      },
      "LayoutGroupSortIndex": 0,
      "Value": 0,
      "Locked": false,
      "Grid": true,
      "Snap": true,
      "IgnoreFoW": false,
      "MeasureMovement": false,
      "DragSelectable": true,
      "Autoraise": true,
      "Sticky": true,
      "Tooltip": true,
      "GridProjection": false,
      "HideWhenFaceDown": false,
      "Hands": false,
      "MaterialIndex": -1,
      "MeshIndex": -1,
      "Bag": {
        "Order": 0
      },
      "LuaScript": "",
      "LuaScriptState": "",
      "XmlUI": "",
      "ContainedObjects": [
        {
          "GUID": "0dc398",
          "Name": "Custom_Assetbundle",
          "Transform": {
            "posX": 9.8620615,
            "posY": 3.04120827,
            "posZ": -4.87849569,
            "rotX": 0.593655765,
            "rotY": 359.985229,
            "rotZ": 359.842865,
            "scaleX": 1.0,
            "scaleY": 1.0,
            "scaleZ": 1.0
          },
          "Nickname": "Sad Violin utton",
          "Description": "",
          "GMNotes": "",
          "AltLookAngle": {
            "x": 0.0,
            "y": 0.0,
            "z": 0.0
          },
          "ColorDiffuse": {
            "r": 0.442999721,
            "g": 0.230999708,
            "b": 0.08999979
          },
          "LayoutGroupSortIndex": 0,
          "Value": 0,
          "Locked": false,
          "Grid": true,
          "Snap": true,
          "IgnoreFoW": false,
          "MeasureMovement": false,
          "DragSelectable": true,
          "Autoraise": true,
          "Sticky": true,
          "Tooltip": true,
          "GridProjection": false,
          "HideWhenFaceDown": false,
          "Hands": false,
          "CustomAssetbundle": {
            "AssetbundleURL": "https://steamusercontent-a.akamaihd.net/ugc/1781715168245646328/B2416C4D4983113455208EF2E2583EF20071D3D5/",
            "AssetbundleSecondaryURL": "",
            "MaterialIndex": 0,
            "TypeIndex": 0,
            "LoopingEffectIndex": 0
          },
          "LuaScript": "--Script based on \"Big, Animated Button\" addon from MrStump and modified by Lan.\r\nfunction buttonPress()\r\n    if lockout == false then\r\n\r\n        self.AssetBundle.playTriggerEffect(0)\r\n        lockout = true\r\n        startLockoutTimer()\r\n    end\r\nend\r\n\r\n\r\nfunction onload()\r\n    self.createButton({\r\n        click_function = \"buttonPress\",\r\n        function_owner = self,  position={0,0.45,0}, height=730, width=730, color = {0,0,0,0}\r\n    })\r\n    self.createButton({\r\n        click_function = \"buttonPress\",\r\n        function_owner = self,  position={0,0.45,0}, rotation={0,11.25,0}, height=730, width=730, color = {0,0,0,0}\r\n    })\r\n    self.createButton({\r\n        click_function = \"buttonPress\",\r\n        function_owner = self,  position={0,0.45,0}, rotation={0,22.5,0}, height=730, width=730, color = {0,0,0,0}\r\n    })\r\n    self.createButton({\r\n        click_function = \"buttonPress\",\r\n        function_owner = self,  position={0,0.45,0}, rotation={0,33.75,0}, height=730, width=730, color = {0,0,0,0}\r\n    })\r\n    self.createButton({\r\n        click_function = \"buttonPress\",\r\n        function_owner = self,  position={0,0.45,0}, rotation={0,45,0}, height=730, width=730, color = {0,0,0,0}\r\n    })\r\n    self.createButton({\r\n        click_function = \"buttonPress\",\r\n        function_owner = self,  position={0,0.45,0}, rotation={0,55.25,0}, height=730, width=730, color = {0,0,0,0}\r\n    })\r\n    self.createButton({\r\n        click_function = \"buttonPress\",\r\n        function_owner = self,  position={0,0.45,0}, rotation={0,77.5,0}, height=730, width=730, color = {0,0,0,0}\r\n    })\r\n    self.createButton({\r\n        click_function = \"buttonPress\",\r\n        function_owner = self,  position={0,0.45,0}, rotation={0,88.75,0}, height=730, width=730, color = {0,0,0,0}\r\n    })\r\n    lockout = false\r\nend\r\n\r\n\r\nfunction startLockoutTimer()\r\n    Timer.create({identifier=self.getGUID(), function_name='unlockLockout', delay=0})\r\nend\r\n\r\n\r\nfunction unlockLockout()\r\n    lockout = false\r\nend\r\n\r\n\r\nfunction onDestroy()\r\n    Timer.destroy(self.getGUID())\r\nend",
          "LuaScriptState": "",
          "XmlUI": ""
        },
        {
          "GUID": "5a7db4",
          "Name": "Custom_Assetbundle",
          "Transform": {
            "posX": 9.092311,
            "posY": 3.03341341,
            "posZ": 1.27279866,
            "rotX": -1.85794579E-05,
            "rotY": 359.985962,
            "rotZ": 1.08009608E-05,
            "scaleX": 1.0,
            "scaleY": 1.0,
            "scaleZ": 1.0
          },
          "Nickname": "Bruh Button",
          "Description": "Bruh",
          "GMNotes": "",
          "AltLookAngle": {
            "x": 0.0,
            "y": 0.0,
            "z": 0.0
          },
          "ColorDiffuse": {
            "r": 1.0,
            "g": 0.0,
            "b": 0.0
          },
          "LayoutGroupSortIndex": 0,
          "Value": 0,
          "Locked": false,
          "Grid": true,
          "Snap": true,
          "IgnoreFoW": false,
          "MeasureMovement": false,
          "DragSelectable": true,
          "Autoraise": true,
          "Sticky": true,
          "Tooltip": true,
          "GridProjection": false,
          "HideWhenFaceDown": false,
          "Hands": false,
          "CustomAssetbundle": {
            "AssetbundleURL": "https://steamusercontent-a.akamaihd.net/ugc/799883014873817488/429E7124F4FF03725B36F371ECA3260C5F2E9E3A/",
            "AssetbundleSecondaryURL": "",
            "MaterialIndex": 0,
            "TypeIndex": 0,
            "LoopingEffectIndex": 0
          },
          "LuaScript": "--Script based on \"Big, Animated Button\" addon from MrStump and modified by Lan.\r\nfunction buttonPress()\r\n    if lockout == false then\r\n\r\n        self.AssetBundle.playTriggerEffect(0)\r\n        lockout = true\r\n        startLockoutTimer()\r\n    end\r\nend\r\n\r\n\r\nfunction onload()\r\n    self.createButton({\r\n        click_function = \"buttonPress\",\r\n        function_owner = self,  position={0,0.45,0}, height=730, width=730, color = {0,0,0,0}\r\n    })\r\n    self.createButton({\r\n        click_function = \"buttonPress\",\r\n        function_owner = self,  position={0,0.45,0}, rotation={0,11.25,0}, height=730, width=730, color = {0,0,0,0}\r\n    })\r\n    self.createButton({\r\n        click_function = \"buttonPress\",\r\n        function_owner = self,  position={0,0.45,0}, rotation={0,22.5,0}, height=730, width=730, color = {0,0,0,0}\r\n    })\r\n    self.createButton({\r\n        click_function = \"buttonPress\",\r\n        function_owner = self,  position={0,0.45,0}, rotation={0,33.75,0}, height=730, width=730, color = {0,0,0,0}\r\n    })\r\n    self.createButton({\r\n        click_function = \"buttonPress\",\r\n        function_owner = self,  position={0,0.45,0}, rotation={0,45,0}, height=730, width=730, color = {0,0,0,0}\r\n    })\r\n    self.createButton({\r\n        click_function = \"buttonPress\",\r\n        function_owner = self,  position={0,0.45,0}, rotation={0,55.25,0}, height=730, width=730, color = {0,0,0,0}\r\n    })\r\n    self.createButton({\r\n        click_function = \"buttonPress\",\r\n        function_owner = self,  position={0,0.45,0}, rotation={0,77.5,0}, height=730, width=730, color = {0,0,0,0}\r\n    })\r\n    self.createButton({\r\n        click_function = \"buttonPress\",\r\n        function_owner = self,  position={0,0.45,0}, rotation={0,88.75,0}, height=730, width=730, color = {0,0,0,0}\r\n    })\r\n    lockout = false\r\nend\r\n\r\n\r\nfunction startLockoutTimer()\r\n    Timer.create({identifier=self.getGUID(), function_name='unlockLockout', delay=0})\r\nend\r\n\r\n\r\nfunction unlockLockout()\r\n    lockout = false\r\nend\r\n\r\n\r\nfunction onDestroy()\r\n    Timer.destroy(self.getGUID())\r\nend",
          "LuaScriptState": "",
          "XmlUI": ""
        },
        {
          "GUID": "1c76e8",
          "Name": "Custom_Assetbundle",
          "Transform": {
            "posX": 0.203968585,
            "posY": 3.033412,
            "posZ": 5.16998243,
            "rotX": -4.606236E-05,
            "rotY": 180.014236,
            "rotZ": -2.32324674E-05,
            "scaleX": 1.0,
            "scaleY": 1.0,
            "scaleZ": 1.0
          },
          "Nickname": "Careless Whisper Button",
          "Description": "",
          "GMNotes": "",
          "AltLookAngle": {
            "x": 0.0,
            "y": 0.0,
            "z": 0.0
          },
          "ColorDiffuse": {
            "r": 0.4275095,
            "g": 0.0,
            "b": 1.0
          },
          "LayoutGroupSortIndex": 0,
          "Value": 0,
          "Locked": false,
          "Grid": true,
          "Snap": true,
          "IgnoreFoW": false,
          "MeasureMovement": false,
          "DragSelectable": true,
          "Autoraise": true,
          "Sticky": true,
          "Tooltip": true,
          "GridProjection": false,
          "HideWhenFaceDown": false,
          "Hands": false,
          "CustomAssetbundle": {
            "AssetbundleURL": "https://steamusercontent-a.akamaihd.net/ugc/1781715029507594776/8175CFB7DB83F4111C7B8EE576C1BB08CE5151E1/",
            "AssetbundleSecondaryURL": "",
            "MaterialIndex": 0,
            "TypeIndex": 0,
            "LoopingEffectIndex": 0
          },
          "LuaScript": "--Script based on \"Big, Animated Button\" addon from MrStump and modified by Lan.\r\nfunction buttonPress()\r\n    if lockout == false then\r\n\r\n        self.AssetBundle.playTriggerEffect(0)\r\n        lockout = true\r\n        startLockoutTimer()\r\n    end\r\nend\r\n\r\n\r\nfunction onload()\r\n    self.createButton({\r\n        click_function = \"buttonPress\",\r\n        function_owner = self,  position={0,0.45,0}, height=730, width=730, color = {0,0,0,0}\r\n    })\r\n    self.createButton({\r\n        click_function = \"buttonPress\",\r\n        function_owner = self,  position={0,0.45,0}, rotation={0,11.25,0}, height=730, width=730, color = {0,0,0,0}\r\n    })\r\n    self.createButton({\r\n        click_function = \"buttonPress\",\r\n        function_owner = self,  position={0,0.45,0}, rotation={0,22.5,0}, height=730, width=730, color = {0,0,0,0}\r\n    })\r\n    self.createButton({\r\n        click_function = \"buttonPress\",\r\n        function_owner = self,  position={0,0.45,0}, rotation={0,33.75,0}, height=730, width=730, color = {0,0,0,0}\r\n    })\r\n    self.createButton({\r\n        click_function = \"buttonPress\",\r\n        function_owner = self,  position={0,0.45,0}, rotation={0,45,0}, height=730, width=730, color = {0,0,0,0}\r\n    })\r\n    self.createButton({\r\n        click_function = \"buttonPress\",\r\n        function_owner = self,  position={0,0.45,0}, rotation={0,55.25,0}, height=730, width=730, color = {0,0,0,0}\r\n    })\r\n    self.createButton({\r\n        click_function = \"buttonPress\",\r\n        function_owner = self,  position={0,0.45,0}, rotation={0,77.5,0}, height=730, width=730, color = {0,0,0,0}\r\n    })\r\n    self.createButton({\r\n        click_function = \"buttonPress\",\r\n        function_owner = self,  position={0,0.45,0}, rotation={0,88.75,0}, height=730, width=730, color = {0,0,0,0}\r\n    })\r\n    lockout = false\r\nend\r\n\r\n\r\nfunction startLockoutTimer()\r\n    Timer.create({identifier=self.getGUID(), function_name='unlockLockout', delay=0})\r\nend\r\n\r\n\r\nfunction unlockLockout()\r\n    lockout = false\r\nend\r\n\r\n\r\nfunction onDestroy()\r\n    Timer.destroy(self.getGUID())\r\nend",
          "LuaScriptState": "",
          "XmlUI": ""
        },
        {
          "GUID": "17653c",
          "Name": "Custom_Assetbundle",
          "Transform": {
            "posX": 7.91997528,
            "posY": 3.03341436,
            "posZ": 5.12884569,
            "rotX": 8.823843E-06,
            "rotY": 179.992325,
            "rotZ": -3.08871381E-06,
            "scaleX": 1.0,
            "scaleY": 1.0,
            "scaleZ": 1.0
          },
          "Nickname": "Oof Button",
          "Description": "",
          "GMNotes": "",
          "AltLookAngle": {
            "x": 0.0,
            "y": 0.0,
            "z": 0.0
          },
          "ColorDiffuse": {
            "r": 1.0,
            "g": 0.5034843,
            "b": 0.5034843
          },
          "LayoutGroupSortIndex": 0,
          "Value": 0,
          "Locked": false,
          "Grid": true,
          "Snap": true,
          "IgnoreFoW": false,
          "MeasureMovement": false,
          "DragSelectable": true,
          "Autoraise": true,
          "Sticky": true,
          "Tooltip": true,
          "GridProjection": false,
          "HideWhenFaceDown": false,
          "Hands": false,
          "CustomAssetbundle": {
            "AssetbundleURL": "https://steamusercontent-a.akamaihd.net/ugc/1781715029507594704/55F1F52238280C9B0622EA690944512AFBE99826/",
            "AssetbundleSecondaryURL": "",
            "MaterialIndex": 0,
            "TypeIndex": 0,
            "LoopingEffectIndex": 0
          },
          "LuaScript": "--Script based on \"Big, Animated Button\" addon from MrStump and modified by Lan.\r\nfunction buttonPress()\r\n    if lockout == false then\r\n\r\n        self.AssetBundle.playTriggerEffect(0)\r\n        lockout = true\r\n        startLockoutTimer()\r\n    end\r\nend\r\n\r\n\r\nfunction onload()\r\n    self.createButton({\r\n        click_function = \"buttonPress\",\r\n        function_owner = self,  position={0,0.45,0}, height=730, width=730, color = {0,0,0,0}\r\n    })\r\n    self.createButton({\r\n        click_function = \"buttonPress\",\r\n        function_owner = self,  position={0,0.45,0}, rotation={0,11.25,0}, height=730, width=730, color = {0,0,0,0}\r\n    })\r\n    self.createButton({\r\n        click_function = \"buttonPress\",\r\n        function_owner = self,  position={0,0.45,0}, rotation={0,22.5,0}, height=730, width=730, color = {0,0,0,0}\r\n    })\r\n    self.createButton({\r\n        click_function = \"buttonPress\",\r\n        function_owner = self,  position={0,0.45,0}, rotation={0,33.75,0}, height=730, width=730, color = {0,0,0,0}\r\n    })\r\n    self.createButton({\r\n        click_function = \"buttonPress\",\r\n        function_owner = self,  position={0,0.45,0}, rotation={0,45,0}, height=730, width=730, color = {0,0,0,0}\r\n    })\r\n    self.createButton({\r\n        click_function = \"buttonPress\",\r\n        function_owner = self,  position={0,0.45,0}, rotation={0,55.25,0}, height=730, width=730, color = {0,0,0,0}\r\n    })\r\n    self.createButton({\r\n        click_function = \"buttonPress\",\r\n        function_owner = self,  position={0,0.45,0}, rotation={0,77.5,0}, height=730, width=730, color = {0,0,0,0}\r\n    })\r\n    self.createButton({\r\n        click_function = \"buttonPress\",\r\n        function_owner = self,  position={0,0.45,0}, rotation={0,88.75,0}, height=730, width=730, color = {0,0,0,0}\r\n    })\r\n    lockout = false\r\nend\r\n\r\n\r\nfunction startLockoutTimer()\r\n    Timer.create({identifier=self.getGUID(), function_name='unlockLockout', delay=0})\r\nend\r\n\r\n\r\nfunction unlockLockout()\r\n    lockout = false\r\nend\r\n\r\n\r\nfunction onDestroy()\r\n    Timer.destroy(self.getGUID())\r\nend",
          "LuaScriptState": "",
          "XmlUI": ""
        },
        {
          "GUID": "b5ce8d",
          "Name": "Custom_Assetbundle",
          "Transform": {
            "posX": 4.012364,
            "posY": 3.03341341,
            "posZ": 6.424893,
            "rotX": 1.375186E-05,
            "rotY": 180.010971,
            "rotZ": -1.468675E-05,
            "scaleX": 1.0,
            "scaleY": 1.0,
            "scaleZ": 1.0
          },
          "Nickname": "Turtle Sex Button",
          "Description": "",
          "GMNotes": "",
          "AltLookAngle": {
            "x": 0.0,
            "y": 0.0,
            "z": 0.0
          },
          "ColorDiffuse": {
            "r": 0.0,
            "g": 1.0,
            "b": 0.219329923
          },
          "LayoutGroupSortIndex": 0,
          "Value": 0,
          "Locked": false,
          "Grid": true,
          "Snap": true,
          "IgnoreFoW": false,
          "MeasureMovement": false,
          "DragSelectable": true,
          "Autoraise": true,
          "Sticky": true,
          "Tooltip": true,
          "GridProjection": false,
          "HideWhenFaceDown": false,
          "Hands": false,
          "CustomAssetbundle": {
            "AssetbundleURL": "https://steamusercontent-a.akamaihd.net/ugc/1781715029507594612/CFE8BC08A7AE16E8E13CCC864A1B0A5D82468186/",
            "AssetbundleSecondaryURL": "",
            "MaterialIndex": 0,
            "TypeIndex": 0,
            "LoopingEffectIndex": 0
          },
          "LuaScript": "--Script based on \"Big, Animated Button\" addon from MrStump and modified by Lan.\r\nfunction buttonPress()\r\n    if lockout == false then\r\n\r\n        self.AssetBundle.playTriggerEffect(0)\r\n        lockout = true\r\n        startLockoutTimer()\r\n    end\r\nend\r\n\r\n\r\nfunction onload()\r\n    self.createButton({\r\n        click_function = \"buttonPress\",\r\n        function_owner = self,  position={0,0.45,0}, height=730, width=730, color = {0,0,0,0}\r\n    })\r\n    self.createButton({\r\n        click_function = \"buttonPress\",\r\n        function_owner = self,  position={0,0.45,0}, rotation={0,11.25,0}, height=730, width=730, color = {0,0,0,0}\r\n    })\r\n    self.createButton({\r\n        click_function = \"buttonPress\",\r\n        function_owner = self,  position={0,0.45,0}, rotation={0,22.5,0}, height=730, width=730, color = {0,0,0,0}\r\n    })\r\n    self.createButton({\r\n        click_function = \"buttonPress\",\r\n        function_owner = self,  position={0,0.45,0}, rotation={0,33.75,0}, height=730, width=730, color = {0,0,0,0}\r\n    })\r\n    self.createButton({\r\n        click_function = \"buttonPress\",\r\n        function_owner = self,  position={0,0.45,0}, rotation={0,45,0}, height=730, width=730, color = {0,0,0,0}\r\n    })\r\n    self.createButton({\r\n        click_function = \"buttonPress\",\r\n        function_owner = self,  position={0,0.45,0}, rotation={0,55.25,0}, height=730, width=730, color = {0,0,0,0}\r\n    })\r\n    self.createButton({\r\n        click_function = \"buttonPress\",\r\n        function_owner = self,  position={0,0.45,0}, rotation={0,77.5,0}, height=730, width=730, color = {0,0,0,0}\r\n    })\r\n    self.createButton({\r\n        click_function = \"buttonPress\",\r\n        function_owner = self,  position={0,0.45,0}, rotation={0,88.75,0}, height=730, width=730, color = {0,0,0,0}\r\n    })\r\n    lockout = false\r\nend\r\n\r\n\r\nfunction startLockoutTimer()\r\n    Timer.create({identifier=self.getGUID(), function_name='unlockLockout', delay=0})\r\nend\r\n\r\n\r\nfunction unlockLockout()\r\n    lockout = false\r\nend\r\n\r\n\r\nfunction onDestroy()\r\n    Timer.destroy(self.getGUID())\r\nend",
          "LuaScriptState": "",
          "XmlUI": ""
        },
        {
          "GUID": "414da2",
          "Name": "Custom_Assetbundle",
          "Transform": {
            "posX": 3.8696785,
            "posY": 3.03341341,
            "posZ": -3.71515179,
            "rotX": -5.018241E-05,
            "rotY": 359.986023,
            "rotZ": 2.793085E-05,
            "scaleX": 1.0,
            "scaleY": 1.0,
            "scaleZ": 1.0
          },
          "Nickname": "YEET Button",
          "Description": "",
          "GMNotes": "",
          "AltLookAngle": {
            "x": 0.0,
            "y": 0.0,
            "z": 0.0
          },
          "ColorDiffuse": {
            "r": 1.0,
            "g": 0.9702607,
            "b": 0.0
          },
          "LayoutGroupSortIndex": 0,
          "Value": 0,
          "Locked": false,
          "Grid": true,
          "Snap": true,
          "IgnoreFoW": false,
          "MeasureMovement": false,
          "DragSelectable": true,
          "Autoraise": true,
          "Sticky": true,
          "Tooltip": true,
          "GridProjection": false,
          "HideWhenFaceDown": false,
          "Hands": false,
          "CustomAssetbundle": {
            "AssetbundleURL": "https://steamusercontent-a.akamaihd.net/ugc/1781715168245646951/58AF63CD81E783DA5222F46972B9F0784B52AD89/",
            "AssetbundleSecondaryURL": "",
            "MaterialIndex": 0,
            "TypeIndex": 0,
            "LoopingEffectIndex": 0
          },
          "LuaScript": "--Script based on \"Big, Animated Button\" addon from MrStump and modified by Lan.\r\nfunction buttonPress()\r\n    if lockout == false then\r\n\r\n        self.AssetBundle.playTriggerEffect(0)\r\n        lockout = true\r\n        startLockoutTimer()\r\n    end\r\nend\r\n\r\n\r\nfunction onload()\r\n    self.createButton({\r\n        click_function = \"buttonPress\",\r\n        function_owner = self,  position={0,0.45,0}, height=730, width=730, color = {0,0,0,0}\r\n    })\r\n    self.createButton({\r\n        click_function = \"buttonPress\",\r\n        function_owner = self,  position={0,0.45,0}, rotation={0,11.25,0}, height=730, width=730, color = {0,0,0,0}\r\n    })\r\n    self.createButton({\r\n        click_function = \"buttonPress\",\r\n        function_owner = self,  position={0,0.45,0}, rotation={0,22.5,0}, height=730, width=730, color = {0,0,0,0}\r\n    })\r\n    self.createButton({\r\n        click_function = \"buttonPress\",\r\n        function_owner = self,  position={0,0.45,0}, rotation={0,33.75,0}, height=730, width=730, color = {0,0,0,0}\r\n    })\r\n    self.createButton({\r\n        click_function = \"buttonPress\",\r\n        function_owner = self,  position={0,0.45,0}, rotation={0,45,0}, height=730, width=730, color = {0,0,0,0}\r\n    })\r\n    self.createButton({\r\n        click_function = \"buttonPress\",\r\n        function_owner = self,  position={0,0.45,0}, rotation={0,55.25,0}, height=730, width=730, color = {0,0,0,0}\r\n    })\r\n    self.createButton({\r\n        click_function = \"buttonPress\",\r\n        function_owner = self,  position={0,0.45,0}, rotation={0,77.5,0}, height=730, width=730, color = {0,0,0,0}\r\n    })\r\n    self.createButton({\r\n        click_function = \"buttonPress\",\r\n        function_owner = self,  position={0,0.45,0}, rotation={0,88.75,0}, height=730, width=730, color = {0,0,0,0}\r\n    })\r\n    lockout = false\r\nend\r\n\r\n\r\nfunction startLockoutTimer()\r\n    Timer.create({identifier=self.getGUID(), function_name='unlockLockout', delay=0})\r\nend\r\n\r\n\r\nfunction unlockLockout()\r\n    lockout = false\r\nend\r\n\r\n\r\nfunction onDestroy()\r\n    Timer.destroy(self.getGUID())\r\nend",
          "LuaScriptState": "",
          "XmlUI": ""
        },
        {
          "GUID": "7ec70d",
          "Name": "Custom_Assetbundle",
          "Transform": {
            "posX": 7.65805626,
            "posY": 3.033414,
            "posZ": -2.45206,
            "rotX": 3.82995167E-05,
            "rotY": 359.986023,
            "rotZ": 1.61584539E-05,
            "scaleX": 1.0,
            "scaleY": 1.0,
            "scaleZ": 1.0
          },
          "Nickname": "Xp Error Button",
          "Description": "",
          "GMNotes": "",
          "AltLookAngle": {
            "x": 0.0,
            "y": 0.0,
            "z": 0.0
          },
          "ColorDiffuse": {
            "r": 0.0,
            "g": 0.888475657,
            "b": 1.0
          },
          "LayoutGroupSortIndex": 0,
          "Value": 0,
          "Locked": false,
          "Grid": true,
          "Snap": true,
          "IgnoreFoW": false,
          "MeasureMovement": false,
          "DragSelectable": true,
          "Autoraise": true,
          "Sticky": true,
          "Tooltip": true,
          "GridProjection": false,
          "HideWhenFaceDown": false,
          "Hands": false,
          "CustomAssetbundle": {
            "AssetbundleURL": "https://steamusercontent-a.akamaihd.net/ugc/1781715168245646790/E6A5F7DD74617DF54E2C75E843953A9F134B07E2/",
            "AssetbundleSecondaryURL": "",
            "MaterialIndex": 0,
            "TypeIndex": 0,
            "LoopingEffectIndex": 0
          },
          "LuaScript": "--Script based on \"Big, Animated Button\" addon from MrStump and modified by Lan.\r\nfunction buttonPress()\r\n    if lockout == false then\r\n\r\n        self.AssetBundle.playTriggerEffect(0)\r\n        lockout = true\r\n        startLockoutTimer()\r\n    end\r\nend\r\n\r\n\r\nfunction onload()\r\n    self.createButton({\r\n        click_function = \"buttonPress\",\r\n        function_owner = self,  position={0,0.45,0}, height=730, width=730, color = {0,0,0,0}\r\n    })\r\n    self.createButton({\r\n        click_function = \"buttonPress\",\r\n        function_owner = self,  position={0,0.45,0}, rotation={0,11.25,0}, height=730, width=730, color = {0,0,0,0}\r\n    })\r\n    self.createButton({\r\n        click_function = \"buttonPress\",\r\n        function_owner = self,  position={0,0.45,0}, rotation={0,22.5,0}, height=730, width=730, color = {0,0,0,0}\r\n    })\r\n    self.createButton({\r\n        click_function = \"buttonPress\",\r\n        function_owner = self,  position={0,0.45,0}, rotation={0,33.75,0}, height=730, width=730, color = {0,0,0,0}\r\n    })\r\n    self.createButton({\r\n        click_function = \"buttonPress\",\r\n        function_owner = self,  position={0,0.45,0}, rotation={0,45,0}, height=730, width=730, color = {0,0,0,0}\r\n    })\r\n    self.createButton({\r\n        click_function = \"buttonPress\",\r\n        function_owner = self,  position={0,0.45,0}, rotation={0,55.25,0}, height=730, width=730, color = {0,0,0,0}\r\n    })\r\n    self.createButton({\r\n        click_function = \"buttonPress\",\r\n        function_owner = self,  position={0,0.45,0}, rotation={0,77.5,0}, height=730, width=730, color = {0,0,0,0}\r\n    })\r\n    self.createButton({\r\n        click_function = \"buttonPress\",\r\n        function_owner = self,  position={0,0.45,0}, rotation={0,88.75,0}, height=730, width=730, color = {0,0,0,0}\r\n    })\r\n    lockout = false\r\nend\r\n\r\n\r\nfunction startLockoutTimer()\r\n    Timer.create({identifier=self.getGUID(), function_name='unlockLockout', delay=0})\r\nend\r\n\r\n\r\nfunction unlockLockout()\r\n    lockout = false\r\nend\r\n\r\n\r\nfunction onDestroy()\r\n    Timer.destroy(self.getGUID())\r\nend",
          "LuaScriptState": "",
          "XmlUI": ""
        },
        {
          "GUID": "026e0e",
          "Name": "Custom_Assetbundle",
          "Transform": {
            "posX": 0.444712222,
            "posY": 3.033413,
            "posZ": -1.83529365,
            "rotX": 3.529011E-06,
            "rotY": 359.986053,
            "rotZ": 1.10381876E-07,
            "scaleX": 1.0,
            "scaleY": 1.0,
            "scaleZ": 1.0
          },
          "Nickname": "Succ Button",
          "Description": "",
          "GMNotes": "",
          "AltLookAngle": {
            "x": 0.0,
            "y": 0.0,
            "z": 0.0
          },
          "ColorDiffuse": {
            "r": 1.0,
            "g": 0.35714218,
            "b": 0.35714218
          },
          "LayoutGroupSortIndex": 0,
          "Value": 0,
          "Locked": false,
          "Grid": true,
          "Snap": true,
          "IgnoreFoW": false,
          "MeasureMovement": false,
          "DragSelectable": true,
          "Autoraise": true,
          "Sticky": true,
          "Tooltip": true,
          "GridProjection": false,
          "HideWhenFaceDown": false,
          "Hands": false,
          "CustomAssetbundle": {
            "AssetbundleURL": "https://steamusercontent-a.akamaihd.net/ugc/1781715168245646622/01EB7FFF20D74377BFFF8E095595AD216BA96CCD/",
            "AssetbundleSecondaryURL": "",
            "MaterialIndex": 0,
            "TypeIndex": 0,
            "LoopingEffectIndex": 0
          },
          "LuaScript": "--Script based on \"Big, Animated Button\" addon from MrStump and modified by Lan.\r\nfunction buttonPress()\r\n    if lockout == false then\r\n\r\n        self.AssetBundle.playTriggerEffect(0)\r\n        lockout = true\r\n        startLockoutTimer()\r\n    end\r\nend\r\n\r\n\r\nfunction onload()\r\n    self.createButton({\r\n        click_function = \"buttonPress\",\r\n        function_owner = self,  position={0,0.45,0}, height=730, width=730, color = {0,0,0,0}\r\n    })\r\n    self.createButton({\r\n        click_function = \"buttonPress\",\r\n        function_owner = self,  position={0,0.45,0}, rotation={0,11.25,0}, height=730, width=730, color = {0,0,0,0}\r\n    })\r\n    self.createButton({\r\n        click_function = \"buttonPress\",\r\n        function_owner = self,  position={0,0.45,0}, rotation={0,22.5,0}, height=730, width=730, color = {0,0,0,0}\r\n    })\r\n    self.createButton({\r\n        click_function = \"buttonPress\",\r\n        function_owner = self,  position={0,0.45,0}, rotation={0,33.75,0}, height=730, width=730, color = {0,0,0,0}\r\n    })\r\n    self.createButton({\r\n        click_function = \"buttonPress\",\r\n        function_owner = self,  position={0,0.45,0}, rotation={0,45,0}, height=730, width=730, color = {0,0,0,0}\r\n    })\r\n    self.createButton({\r\n        click_function = \"buttonPress\",\r\n        function_owner = self,  position={0,0.45,0}, rotation={0,55.25,0}, height=730, width=730, color = {0,0,0,0}\r\n    })\r\n    self.createButton({\r\n        click_function = \"buttonPress\",\r\n        function_owner = self,  position={0,0.45,0}, rotation={0,77.5,0}, height=730, width=730, color = {0,0,0,0}\r\n    })\r\n    self.createButton({\r\n        click_function = \"buttonPress\",\r\n        function_owner = self,  position={0,0.45,0}, rotation={0,88.75,0}, height=730, width=730, color = {0,0,0,0}\r\n    })\r\n    lockout = false\r\nend\r\n\r\n\r\nfunction startLockoutTimer()\r\n    Timer.create({identifier=self.getGUID(), function_name='unlockLockout', delay=0})\r\nend\r\n\r\n\r\nfunction unlockLockout()\r\n    lockout = false\r\nend\r\n\r\n\r\nfunction onDestroy()\r\n    Timer.destroy(self.getGUID())\r\nend",
          "LuaScriptState": "",
          "XmlUI": ""
        },
        {
          "GUID": "cd387e",
          "Name": "Custom_Assetbundle",
          "Transform": {
            "posX": -1.16565418,
            "posY": 3.03346252,
            "posZ": 1.492508,
            "rotX": 5.28888449E-06,
            "rotY": 359.9861,
            "rotZ": 5.17513672E-06,
            "scaleX": 1.0,
            "scaleY": 1.0,
            "scaleZ": 1.0
          },
          "Nickname": "Steam Incoming Button",
          "Description": "",
          "GMNotes": "",
          "AltLookAngle": {
            "x": 0.0,
            "y": 0.0,
            "z": 0.0
          },
          "ColorDiffuse": {
            "r": 0.0,
            "g": 0.0,
            "b": 0.0
          },
          "LayoutGroupSortIndex": 0,
          "Value": 0,
          "Locked": false,
          "Grid": true,
          "Snap": true,
          "IgnoreFoW": false,
          "MeasureMovement": false,
          "DragSelectable": true,
          "Autoraise": true,
          "Sticky": true,
          "Tooltip": true,
          "GridProjection": false,
          "HideWhenFaceDown": false,
          "Hands": false,
          "CustomAssetbundle": {
            "AssetbundleURL": "https://steamusercontent-a.akamaihd.net/ugc/1781715168245646485/FDF5E35B0896B9392B35D3BDCA7496E96C0E1511/",
            "AssetbundleSecondaryURL": "",
            "MaterialIndex": 0,
            "TypeIndex": 0,
            "LoopingEffectIndex": 0
          },
          "LuaScript": "--Script based on \"Big, Animated Button\" addon from MrStump and modified by Lan.\r\nfunction buttonPress()\r\n    if lockout == false then\r\n\r\n        self.AssetBundle.playTriggerEffect(0)\r\n        lockout = true\r\n        startLockoutTimer()\r\n    end\r\nend\r\n\r\n\r\nfunction onload()\r\n    self.createButton({\r\n        click_function = \"buttonPress\",\r\n        function_owner = self,  position={0,0.45,0}, height=730, width=730, color = {0,0,0,0}\r\n    })\r\n    self.createButton({\r\n        click_function = \"buttonPress\",\r\n        function_owner = self,  position={0,0.45,0}, rotation={0,11.25,0}, height=730, width=730, color = {0,0,0,0}\r\n    })\r\n    self.createButton({\r\n        click_function = \"buttonPress\",\r\n        function_owner = self,  position={0,0.45,0}, rotation={0,22.5,0}, height=730, width=730, color = {0,0,0,0}\r\n    })\r\n    self.createButton({\r\n        click_function = \"buttonPress\",\r\n        function_owner = self,  position={0,0.45,0}, rotation={0,33.75,0}, height=730, width=730, color = {0,0,0,0}\r\n    })\r\n    self.createButton({\r\n        click_function = \"buttonPress\",\r\n        function_owner = self,  position={0,0.45,0}, rotation={0,45,0}, height=730, width=730, color = {0,0,0,0}\r\n    })\r\n    self.createButton({\r\n        click_function = \"buttonPress\",\r\n        function_owner = self,  position={0,0.45,0}, rotation={0,55.25,0}, height=730, width=730, color = {0,0,0,0}\r\n    })\r\n    self.createButton({\r\n        click_function = \"buttonPress\",\r\n        function_owner = self,  position={0,0.45,0}, rotation={0,77.5,0}, height=730, width=730, color = {0,0,0,0}\r\n    })\r\n    self.createButton({\r\n        click_function = \"buttonPress\",\r\n        function_owner = self,  position={0,0.45,0}, rotation={0,88.75,0}, height=730, width=730, color = {0,0,0,0}\r\n    })\r\n    lockout = false\r\nend\r\n\r\n\r\nfunction startLockoutTimer()\r\n    Timer.create({identifier=self.getGUID(), function_name='unlockLockout', delay=0})\r\nend\r\n\r\n\r\nfunction unlockLockout()\r\n    lockout = false\r\nend\r\n\r\n\r\nfunction onDestroy()\r\n    Timer.destroy(self.getGUID())\r\nend",
          "LuaScriptState": "",
          "XmlUI": ""
        },
        {
          "GUID": "8b833a",
          "Name": "Custom_Assetbundle",
          "Transform": {
            "posX": 3.93357515,
            "posY": 3.03341436,
            "posZ": -6.881741,
            "rotX": -4.94561755E-06,
            "rotY": 359.986,
            "rotZ": 1.9916235E-05,
            "scaleX": 1.0,
            "scaleY": 1.0,
            "scaleZ": 1.0
          },
          "Nickname": "Sad Trombone Button",
          "Description": "Bruh",
          "GMNotes": "",
          "AltLookAngle": {
            "x": 0.0,
            "y": 0.0,
            "z": 0.0
          },
          "ColorDiffuse": {
            "r": 0.9559999,
            "g": 0.3919997,
            "b": 0.112999715
          },
          "LayoutGroupSortIndex": 0,
          "Value": 0,
          "Locked": false,
          "Grid": true,
          "Snap": true,
          "IgnoreFoW": false,
          "MeasureMovement": false,
          "DragSelectable": true,
          "Autoraise": true,
          "Sticky": true,
          "Tooltip": true,
          "GridProjection": false,
          "HideWhenFaceDown": false,
          "Hands": false,
          "CustomAssetbundle": {
            "AssetbundleURL": "https://steamusercontent-a.akamaihd.net/ugc/1781715168245646184/97D74A930E0C33114E41D5A94260534C6CA7D947/",
            "AssetbundleSecondaryURL": "",
            "MaterialIndex": 0,
            "TypeIndex": 0,
            "LoopingEffectIndex": 0
          },
          "LuaScript": "--Script based on \"Big, Animated Button\" addon from MrStump and modified by Lan.\r\nfunction buttonPress()\r\n    if lockout == false then\r\n\r\n        self.AssetBundle.playTriggerEffect(0)\r\n        lockout = true\r\n        startLockoutTimer()\r\n    end\r\nend\r\n\r\n\r\nfunction onload()\r\n    self.createButton({\r\n        click_function = \"buttonPress\",\r\n        function_owner = self,  position={0,0.45,0}, height=730, width=730, color = {0,0,0,0}\r\n    })\r\n    self.createButton({\r\n        click_function = \"buttonPress\",\r\n        function_owner = self,  position={0,0.45,0}, rotation={0,11.25,0}, height=730, width=730, color = {0,0,0,0}\r\n    })\r\n    self.createButton({\r\n        click_function = \"buttonPress\",\r\n        function_owner = self,  position={0,0.45,0}, rotation={0,22.5,0}, height=730, width=730, color = {0,0,0,0}\r\n    })\r\n    self.createButton({\r\n        click_function = \"buttonPress\",\r\n        function_owner = self,  position={0,0.45,0}, rotation={0,33.75,0}, height=730, width=730, color = {0,0,0,0}\r\n    })\r\n    self.createButton({\r\n        click_function = \"buttonPress\",\r\n        function_owner = self,  position={0,0.45,0}, rotation={0,45,0}, height=730, width=730, color = {0,0,0,0}\r\n    })\r\n    self.createButton({\r\n        click_function = \"buttonPress\",\r\n        function_owner = self,  position={0,0.45,0}, rotation={0,55.25,0}, height=730, width=730, color = {0,0,0,0}\r\n    })\r\n    self.createButton({\r\n        click_function = \"buttonPress\",\r\n        function_owner = self,  position={0,0.45,0}, rotation={0,77.5,0}, height=730, width=730, color = {0,0,0,0}\r\n    })\r\n    self.createButton({\r\n        click_function = \"buttonPress\",\r\n        function_owner = self,  position={0,0.45,0}, rotation={0,88.75,0}, height=730, width=730, color = {0,0,0,0}\r\n    })\r\n    lockout = false\r\nend\r\n\r\n\r\nfunction startLockoutTimer()\r\n    Timer.create({identifier=self.getGUID(), function_name='unlockLockout', delay=0})\r\nend\r\n\r\n\r\nfunction unlockLockout()\r\n    lockout = false\r\nend\r\n\r\n\r\nfunction onDestroy()\r\n    Timer.destroy(self.getGUID())\r\nend",
          "LuaScriptState": "",
          "XmlUI": ""
        },
        {
          "GUID": "c2abc6",
          "Name": "Custom_Assetbundle",
          "Transform": {
            "posX": -2.215405,
            "posY": 3.03341246,
            "posZ": -4.391953,
            "rotX": -8.216416E-06,
            "rotY": 359.986481,
            "rotZ": 2.70223336E-06,
            "scaleX": 1.0,
            "scaleY": 1.0,
            "scaleZ": 1.0
          },
          "Nickname": "Pussy Button",
          "Description": "",
          "GMNotes": "",
          "AltLookAngle": {
            "x": 0.0,
            "y": 0.0,
            "z": 0.0
          },
          "ColorDiffuse": {
            "r": 0.96,
            "g": 0.438999742,
            "b": 0.807
          },
          "LayoutGroupSortIndex": 0,
          "Value": 0,
          "Locked": false,
          "Grid": true,
          "Snap": true,
          "IgnoreFoW": false,
          "MeasureMovement": false,
          "DragSelectable": true,
          "Autoraise": true,
          "Sticky": true,
          "Tooltip": true,
          "GridProjection": false,
          "HideWhenFaceDown": false,
          "Hands": false,
          "CustomAssetbundle": {
            "AssetbundleURL": "https://steamusercontent-a.akamaihd.net/ugc/1781715168245646043/CB7BDA494990BF629C584B9705AE2BB64F842C02/",
            "AssetbundleSecondaryURL": "",
            "MaterialIndex": 0,
            "TypeIndex": 0,
            "LoopingEffectIndex": 0
          },
          "LuaScript": "--Script based on \"Big, Animated Button\" addon from MrStump and modified by Lan.\r\nfunction buttonPress()\r\n    if lockout == false then\r\n\r\n        self.AssetBundle.playTriggerEffect(0)\r\n        lockout = true\r\n        startLockoutTimer()\r\n    end\r\nend\r\n\r\n\r\nfunction onload()\r\n    self.createButton({\r\n        click_function = \"buttonPress\",\r\n        function_owner = self,  position={0,0.45,0}, height=730, width=730, color = {0,0,0,0}\r\n    })\r\n    self.createButton({\r\n        click_function = \"buttonPress\",\r\n        function_owner = self,  position={0,0.45,0}, rotation={0,11.25,0}, height=730, width=730, color = {0,0,0,0}\r\n    })\r\n    self.createButton({\r\n        click_function = \"buttonPress\",\r\n        function_owner = self,  position={0,0.45,0}, rotation={0,22.5,0}, height=730, width=730, color = {0,0,0,0}\r\n    })\r\n    self.createButton({\r\n        click_function = \"buttonPress\",\r\n        function_owner = self,  position={0,0.45,0}, rotation={0,33.75,0}, height=730, width=730, color = {0,0,0,0}\r\n    })\r\n    self.createButton({\r\n        click_function = \"buttonPress\",\r\n        function_owner = self,  position={0,0.45,0}, rotation={0,45,0}, height=730, width=730, color = {0,0,0,0}\r\n    })\r\n    self.createButton({\r\n        click_function = \"buttonPress\",\r\n        function_owner = self,  position={0,0.45,0}, rotation={0,55.25,0}, height=730, width=730, color = {0,0,0,0}\r\n    })\r\n    self.createButton({\r\n        click_function = \"buttonPress\",\r\n        function_owner = self,  position={0,0.45,0}, rotation={0,77.5,0}, height=730, width=730, color = {0,0,0,0}\r\n    })\r\n    self.createButton({\r\n        click_function = \"buttonPress\",\r\n        function_owner = self,  position={0,0.45,0}, rotation={0,88.75,0}, height=730, width=730, color = {0,0,0,0}\r\n    })\r\n    lockout = false\r\nend\r\n\r\n\r\nfunction startLockoutTimer()\r\n    Timer.create({identifier=self.getGUID(), function_name='unlockLockout', delay=0})\r\nend\r\n\r\n\r\nfunction unlockLockout()\r\n    lockout = false\r\nend\r\n\r\n\r\nfunction onDestroy()\r\n    Timer.destroy(self.getGUID())\r\nend",
          "LuaScriptState": "",
          "XmlUI": ""
        },
        {
          "GUID": "34b1ab",
          "Name": "Custom_Assetbundle",
          "Transform": {
            "posX": -5.011346,
            "posY": 3.033458,
            "posZ": 1.42084229,
            "rotX": 5.920433E-06,
            "rotY": 359.986023,
            "rotZ": 6.84340648E-06,
            "scaleX": 1.0,
            "scaleY": 1.0,
            "scaleZ": 1.0
          },
          "Nickname": "Nut Button",
          "Description": "",
          "GMNotes": "",
          "AltLookAngle": {
            "x": 0.0,
            "y": 0.0,
            "z": 0.0
          },
          "ColorDiffuse": {
            "r": 1.0,
            "g": 1.0,
            "b": 1.0
          },
          "LayoutGroupSortIndex": 0,
          "Value": 0,
          "Locked": false,
          "Grid": true,
          "Snap": true,
          "IgnoreFoW": false,
          "MeasureMovement": false,
          "DragSelectable": true,
          "Autoraise": true,
          "Sticky": true,
          "Tooltip": true,
          "GridProjection": false,
          "HideWhenFaceDown": false,
          "Hands": false,
          "CustomAssetbundle": {
            "AssetbundleURL": "https://steamusercontent-a.akamaihd.net/ugc/1781715168245645893/F38EB564285ED44AFD618C6F0782698226BAE140/",
            "AssetbundleSecondaryURL": "",
            "MaterialIndex": 0,
            "TypeIndex": 0,
            "LoopingEffectIndex": 0
          },
          "LuaScript": "--Script based on \"Big, Animated Button\" addon from MrStump and modified by Lan.\r\nfunction buttonPress()\r\n    if lockout == false then\r\n\r\n        self.AssetBundle.playTriggerEffect(0)\r\n        lockout = true\r\n        startLockoutTimer()\r\n    end\r\nend\r\n\r\n\r\nfunction onload()\r\n    self.createButton({\r\n        click_function = \"buttonPress\",\r\n        function_owner = self,  position={0,0.45,0}, height=730, width=730, color = {0,0,0,0}\r\n    })\r\n    self.createButton({\r\n        click_function = \"buttonPress\",\r\n        function_owner = self,  position={0,0.45,0}, rotation={0,11.25,0}, height=730, width=730, color = {0,0,0,0}\r\n    })\r\n    self.createButton({\r\n        click_function = \"buttonPress\",\r\n        function_owner = self,  position={0,0.45,0}, rotation={0,22.5,0}, height=730, width=730, color = {0,0,0,0}\r\n    })\r\n    self.createButton({\r\n        click_function = \"buttonPress\",\r\n        function_owner = self,  position={0,0.45,0}, rotation={0,33.75,0}, height=730, width=730, color = {0,0,0,0}\r\n    })\r\n    self.createButton({\r\n        click_function = \"buttonPress\",\r\n        function_owner = self,  position={0,0.45,0}, rotation={0,45,0}, height=730, width=730, color = {0,0,0,0}\r\n    })\r\n    self.createButton({\r\n        click_function = \"buttonPress\",\r\n        function_owner = self,  position={0,0.45,0}, rotation={0,55.25,0}, height=730, width=730, color = {0,0,0,0}\r\n    })\r\n    self.createButton({\r\n        click_function = \"buttonPress\",\r\n        function_owner = self,  position={0,0.45,0}, rotation={0,77.5,0}, height=730, width=730, color = {0,0,0,0}\r\n    })\r\n    self.createButton({\r\n        click_function = \"buttonPress\",\r\n        function_owner = self,  position={0,0.45,0}, rotation={0,88.75,0}, height=730, width=730, color = {0,0,0,0}\r\n    })\r\n    lockout = false\r\nend\r\n\r\n\r\nfunction startLockoutTimer()\r\n    Timer.create({identifier=self.getGUID(), function_name='unlockLockout', delay=0})\r\nend\r\n\r\n\r\nfunction unlockLockout()\r\n    lockout = false\r\nend\r\n\r\n\r\nfunction onDestroy()\r\n    Timer.destroy(self.getGUID())\r\nend",
          "LuaScriptState": "",
          "XmlUI": ""
        },
        {
          "GUID": "cc14e7",
          "Name": "Custom_Assetbundle",
          "Transform": {
            "posX": -2.71959448,
            "posY": 3.03341317,
            "posZ": 7.85322428,
            "rotX": 3.01100736E-05,
            "rotY": 359.986,
            "rotZ": -2.900156E-05,
            "scaleX": 1.0,
            "scaleY": 1.0,
            "scaleZ": 1.0
          },
          "Nickname": "NOPE Button",
          "Description": "",
          "GMNotes": "",
          "AltLookAngle": {
            "x": 0.0,
            "y": 0.0,
            "z": 0.0
          },
          "ColorDiffuse": {
            "r": 0.3397209,
            "g": 0.3397209,
            "b": 0.3397209
          },
          "LayoutGroupSortIndex": 0,
          "Value": 0,
          "Locked": false,
          "Grid": true,
          "Snap": true,
          "IgnoreFoW": false,
          "MeasureMovement": false,
          "DragSelectable": true,
          "Autoraise": true,
          "Sticky": true,
          "Tooltip": true,
          "GridProjection": false,
          "HideWhenFaceDown": false,
          "Hands": false,
          "CustomAssetbundle": {
            "AssetbundleURL": "https://steamusercontent-a.akamaihd.net/ugc/1781715168245645741/123A0C6950765894E7DD79D3FAE598256FC8538C/",
            "AssetbundleSecondaryURL": "",
            "MaterialIndex": 0,
            "TypeIndex": 0,
            "LoopingEffectIndex": 0
          },
          "LuaScript": "--Script based on \"Big, Animated Button\" addon from MrStump and modified by Lan.\r\nfunction buttonPress()\r\n    if lockout == false then\r\n\r\n        self.AssetBundle.playTriggerEffect(0)\r\n        lockout = true\r\n        startLockoutTimer()\r\n    end\r\nend\r\n\r\n\r\nfunction onload()\r\n    self.createButton({\r\n        click_function = \"buttonPress\",\r\n        function_owner = self,  position={0,0.45,0}, height=730, width=730, color = {0,0,0,0}\r\n    })\r\n    self.createButton({\r\n        click_function = \"buttonPress\",\r\n        function_owner = self,  position={0,0.45,0}, rotation={0,11.25,0}, height=730, width=730, color = {0,0,0,0}\r\n    })\r\n    self.createButton({\r\n        click_function = \"buttonPress\",\r\n        function_owner = self,  position={0,0.45,0}, rotation={0,22.5,0}, height=730, width=730, color = {0,0,0,0}\r\n    })\r\n    self.createButton({\r\n        click_function = \"buttonPress\",\r\n        function_owner = self,  position={0,0.45,0}, rotation={0,33.75,0}, height=730, width=730, color = {0,0,0,0}\r\n    })\r\n    self.createButton({\r\n        click_function = \"buttonPress\",\r\n        function_owner = self,  position={0,0.45,0}, rotation={0,45,0}, height=730, width=730, color = {0,0,0,0}\r\n    })\r\n    self.createButton({\r\n        click_function = \"buttonPress\",\r\n        function_owner = self,  position={0,0.45,0}, rotation={0,55.25,0}, height=730, width=730, color = {0,0,0,0}\r\n    })\r\n    self.createButton({\r\n        click_function = \"buttonPress\",\r\n        function_owner = self,  position={0,0.45,0}, rotation={0,77.5,0}, height=730, width=730, color = {0,0,0,0}\r\n    })\r\n    self.createButton({\r\n        click_function = \"buttonPress\",\r\n        function_owner = self,  position={0,0.45,0}, rotation={0,88.75,0}, height=730, width=730, color = {0,0,0,0}\r\n    })\r\n    lockout = false\r\nend\r\n\r\n\r\nfunction startLockoutTimer()\r\n    Timer.create({identifier=self.getGUID(), function_name='unlockLockout', delay=0})\r\nend\r\n\r\n\r\nfunction unlockLockout()\r\n    lockout = false\r\nend\r\n\r\n\r\nfunction onDestroy()\r\n    Timer.destroy(self.getGUID())\r\nend",
          "LuaScriptState": "",
          "XmlUI": ""
        },
        {
          "GUID": "259b99",
          "Name": "Custom_Assetbundle",
          "Transform": {
            "posX": 4.00729275,
            "posY": 3.033413,
            "posZ": 10.0101643,
            "rotX": -3.212032E-05,
            "rotY": 359.986,
            "rotZ": -1.555851E-05,
            "scaleX": 1.0,
            "scaleY": 1.0,
            "scaleZ": 1.0
          },
          "Nickname": "MLG Airhorn Button",
          "Description": "",
          "GMNotes": "",
          "AltLookAngle": {
            "x": 0.0,
            "y": 0.0,
            "z": 0.0
          },
          "ColorDiffuse": {
            "r": 0.191999733,
            "g": 0.701,
            "b": 0.167999715
          },
          "LayoutGroupSortIndex": 0,
          "Value": 0,
          "Locked": false,
          "Grid": true,
          "Snap": true,
          "IgnoreFoW": false,
          "MeasureMovement": false,
          "DragSelectable": true,
          "Autoraise": true,
          "Sticky": true,
          "Tooltip": true,
          "GridProjection": false,
          "HideWhenFaceDown": false,
          "Hands": false,
          "CustomAssetbundle": {
            "AssetbundleURL": "https://steamusercontent-a.akamaihd.net/ugc/1781715168245645540/CFFD44C7797559851DE637C8593E9C7E08CF9652/",
            "AssetbundleSecondaryURL": "",
            "MaterialIndex": 0,
            "TypeIndex": 0,
            "LoopingEffectIndex": 0
          },
          "LuaScript": "--Script based on \"Big, Animated Button\" addon from MrStump and modified by Lan.\r\nfunction buttonPress()\r\n    if lockout == false then\r\n\r\n        self.AssetBundle.playTriggerEffect(0)\r\n        lockout = true\r\n        startLockoutTimer()\r\n    end\r\nend\r\n\r\n\r\nfunction onload()\r\n    self.createButton({\r\n        click_function = \"buttonPress\",\r\n        function_owner = self,  position={0,0.45,0}, height=730, width=730, color = {0,0,0,0}\r\n    })\r\n    self.createButton({\r\n        click_function = \"buttonPress\",\r\n        function_owner = self,  position={0,0.45,0}, rotation={0,11.25,0}, height=730, width=730, color = {0,0,0,0}\r\n    })\r\n    self.createButton({\r\n        click_function = \"buttonPress\",\r\n        function_owner = self,  position={0,0.45,0}, rotation={0,22.5,0}, height=730, width=730, color = {0,0,0,0}\r\n    })\r\n    self.createButton({\r\n        click_function = \"buttonPress\",\r\n        function_owner = self,  position={0,0.45,0}, rotation={0,33.75,0}, height=730, width=730, color = {0,0,0,0}\r\n    })\r\n    self.createButton({\r\n        click_function = \"buttonPress\",\r\n        function_owner = self,  position={0,0.45,0}, rotation={0,45,0}, height=730, width=730, color = {0,0,0,0}\r\n    })\r\n    self.createButton({\r\n        click_function = \"buttonPress\",\r\n        function_owner = self,  position={0,0.45,0}, rotation={0,55.25,0}, height=730, width=730, color = {0,0,0,0}\r\n    })\r\n    self.createButton({\r\n        click_function = \"buttonPress\",\r\n        function_owner = self,  position={0,0.45,0}, rotation={0,77.5,0}, height=730, width=730, color = {0,0,0,0}\r\n    })\r\n    self.createButton({\r\n        click_function = \"buttonPress\",\r\n        function_owner = self,  position={0,0.45,0}, rotation={0,88.75,0}, height=730, width=730, color = {0,0,0,0}\r\n    })\r\n    lockout = false\r\nend\r\n\r\n\r\nfunction startLockoutTimer()\r\n    Timer.create({identifier=self.getGUID(), function_name='unlockLockout', delay=0})\r\nend\r\n\r\n\r\nfunction unlockLockout()\r\n    lockout = false\r\nend\r\n\r\n\r\nfunction onDestroy()\r\n    Timer.destroy(self.getGUID())\r\nend",
          "LuaScriptState": "",
          "XmlUI": ""
        },
        {
          "GUID": "fa5ac2",
          "Name": "Custom_Assetbundle",
          "Transform": {
            "posX": 10.5321,
            "posY": 3.03341365,
            "posZ": 7.628165,
            "rotX": 1.7895165E-05,
            "rotY": 359.984924,
            "rotZ": -9.857851E-08,
            "scaleX": 1.0,
            "scaleY": 1.0,
            "scaleZ": 1.0
          },
          "Nickname": "Inception Button",
          "Description": "",
          "GMNotes": "",
          "AltLookAngle": {
            "x": 0.0,
            "y": 0.0,
            "z": 0.0
          },
          "ColorDiffuse": {
            "r": 0.12899971,
            "g": 0.694,
            "b": 0.606999934
          },
          "LayoutGroupSortIndex": 0,
          "Value": 0,
          "Locked": false,
          "Grid": true,
          "Snap": true,
          "IgnoreFoW": false,
          "MeasureMovement": false,
          "DragSelectable": true,
          "Autoraise": true,
          "Sticky": true,
          "Tooltip": true,
          "GridProjection": false,
          "HideWhenFaceDown": false,
          "Hands": false,
          "CustomAssetbundle": {
            "AssetbundleURL": "https://steamusercontent-a.akamaihd.net/ugc/1781715168245645322/A512FF83A8162E187008532AA9C7FB4A5C61EDFB/",
            "AssetbundleSecondaryURL": "",
            "MaterialIndex": 0,
            "TypeIndex": 0,
            "LoopingEffectIndex": 0
          },
          "LuaScript": "--Script based on \"Big, Animated Button\" addon from MrStump and modified by Lan.\r\nfunction buttonPress()\r\n    if lockout == false then\r\n\r\n        self.AssetBundle.playTriggerEffect(0)\r\n        lockout = true\r\n        startLockoutTimer()\r\n    end\r\nend\r\n\r\n\r\nfunction onload()\r\n    self.createButton({\r\n        click_function = \"buttonPress\",\r\n        function_owner = self,  position={0,0.45,0}, height=730, width=730, color = {0,0,0,0}\r\n    })\r\n    self.createButton({\r\n        click_function = \"buttonPress\",\r\n        function_owner = self,  position={0,0.45,0}, rotation={0,11.25,0}, height=730, width=730, color = {0,0,0,0}\r\n    })\r\n    self.createButton({\r\n        click_function = \"buttonPress\",\r\n        function_owner = self,  position={0,0.45,0}, rotation={0,22.5,0}, height=730, width=730, color = {0,0,0,0}\r\n    })\r\n    self.createButton({\r\n        click_function = \"buttonPress\",\r\n        function_owner = self,  position={0,0.45,0}, rotation={0,33.75,0}, height=730, width=730, color = {0,0,0,0}\r\n    })\r\n    self.createButton({\r\n        click_function = \"buttonPress\",\r\n        function_owner = self,  position={0,0.45,0}, rotation={0,45,0}, height=730, width=730, color = {0,0,0,0}\r\n    })\r\n    self.createButton({\r\n        click_function = \"buttonPress\",\r\n        function_owner = self,  position={0,0.45,0}, rotation={0,55.25,0}, height=730, width=730, color = {0,0,0,0}\r\n    })\r\n    self.createButton({\r\n        click_function = \"buttonPress\",\r\n        function_owner = self,  position={0,0.45,0}, rotation={0,77.5,0}, height=730, width=730, color = {0,0,0,0}\r\n    })\r\n    self.createButton({\r\n        click_function = \"buttonPress\",\r\n        function_owner = self,  position={0,0.45,0}, rotation={0,88.75,0}, height=730, width=730, color = {0,0,0,0}\r\n    })\r\n    lockout = false\r\nend\r\n\r\n\r\nfunction startLockoutTimer()\r\n    Timer.create({identifier=self.getGUID(), function_name='unlockLockout', delay=0})\r\nend\r\n\r\n\r\nfunction unlockLockout()\r\n    lockout = false\r\nend\r\n\r\n\r\nfunction onDestroy()\r\n    Timer.destroy(self.getGUID())\r\nend",
          "LuaScriptState": "",
          "XmlUI": ""
        },
        {
          "GUID": "87b5dd",
          "Name": "Custom_Assetbundle",
          "Transform": {
            "posX": 12.7997246,
            "posY": 3.03341341,
            "posZ": 1.43895781,
            "rotX": 2.23949537E-05,
            "rotY": 359.986023,
            "rotZ": 4.05777246E-06,
            "scaleX": 1.0,
            "scaleY": 1.0,
            "scaleZ": 1.0
          },
          "Nickname": "Fart Button",
          "Description": "",
          "GMNotes": "",
          "AltLookAngle": {
            "x": 0.0,
            "y": 0.0,
            "z": 0.0
          },
          "ColorDiffuse": {
            "r": 0.6602788,
            "g": 0.340722,
            "b": 0.1276843
          },
          "LayoutGroupSortIndex": 0,
          "Value": 0,
          "Locked": false,
          "Grid": true,
          "Snap": true,
          "IgnoreFoW": false,
          "MeasureMovement": false,
          "DragSelectable": true,
          "Autoraise": true,
          "Sticky": true,
          "Tooltip": true,
          "GridProjection": false,
          "HideWhenFaceDown": false,
          "Hands": false,
          "CustomAssetbundle": {
            "AssetbundleURL": "https://steamusercontent-a.akamaihd.net/ugc/1781715168245645167/9159DE7F2D16B1A2E491DBC1D6566A1F8AFC187B/",
            "AssetbundleSecondaryURL": "",
            "MaterialIndex": 0,
            "TypeIndex": 0,
            "LoopingEffectIndex": 0
          },
          "LuaScript": "--Script based on \"Big, Animated Button\" addon from MrStump and modified by Lan.\r\nfunction buttonPress()\r\n    if lockout == false then\r\n\r\n        self.AssetBundle.playTriggerEffect(0)\r\n        lockout = true\r\n        startLockoutTimer()\r\n    end\r\nend\r\n\r\n\r\nfunction onload()\r\n    self.createButton({\r\n        click_function = \"buttonPress\",\r\n        function_owner = self,  position={0,0.45,0}, height=730, width=730, color = {0,0,0,0}\r\n    })\r\n    self.createButton({\r\n        click_function = \"buttonPress\",\r\n        function_owner = self,  position={0,0.45,0}, rotation={0,11.25,0}, height=730, width=730, color = {0,0,0,0}\r\n    })\r\n    self.createButton({\r\n        click_function = \"buttonPress\",\r\n        function_owner = self,  position={0,0.45,0}, rotation={0,22.5,0}, height=730, width=730, color = {0,0,0,0}\r\n    })\r\n    self.createButton({\r\n        click_function = \"buttonPress\",\r\n        function_owner = self,  position={0,0.45,0}, rotation={0,33.75,0}, height=730, width=730, color = {0,0,0,0}\r\n    })\r\n    self.createButton({\r\n        click_function = \"buttonPress\",\r\n        function_owner = self,  position={0,0.45,0}, rotation={0,45,0}, height=730, width=730, color = {0,0,0,0}\r\n    })\r\n    self.createButton({\r\n        click_function = \"buttonPress\",\r\n        function_owner = self,  position={0,0.45,0}, rotation={0,55.25,0}, height=730, width=730, color = {0,0,0,0}\r\n    })\r\n    self.createButton({\r\n        click_function = \"buttonPress\",\r\n        function_owner = self,  position={0,0.45,0}, rotation={0,77.5,0}, height=730, width=730, color = {0,0,0,0}\r\n    })\r\n    self.createButton({\r\n        click_function = \"buttonPress\",\r\n        function_owner = self,  position={0,0.45,0}, rotation={0,88.75,0}, height=730, width=730, color = {0,0,0,0}\r\n    })\r\n    lockout = false\r\nend\r\n\r\n\r\nfunction startLockoutTimer()\r\n    Timer.create({identifier=self.getGUID(), function_name='unlockLockout', delay=0})\r\nend\r\n\r\n\r\nfunction unlockLockout()\r\n    lockout = false\r\nend\r\n\r\n\r\nfunction onDestroy()\r\n    Timer.destroy(self.getGUID())\r\nend",
          "LuaScriptState": "",
          "XmlUI": ""
        }
      ]
    }
  ]
}